upcpayment/Upc_payment.py
upcpayment/Upc_payment_xml.py
upcpayment/__init__.py
upcpayment/exceptions.py
upcpayment-0.5.5.7.8.3.dist-info/METADATA
upcpayment-0.5.5.7.8.3.dist-info/WHEEL
upcpayment-0.5.5.7.8.3.dist-info/top_level.txt
upcpayment-0.5.5.7.8.3.dist-info/RECORD
