Metadata-Version: 2.1
Name: upcpayment
Version: 0.5.5.7.8.3
Summary: Library for upc services
Home-page: https://github.com/upcecconnect/PythonSDK
Author: Valentyn Ishchenko
Author-email: xalikxalik44@gmail.com
License: UNKNOWN
Platform: UNKNOWN
Classifier: Programming Language :: Python :: 3
Classifier: Programming Language :: Python :: 3.7
Classifier: License :: OSI Approved :: MIT License
Classifier: Operating System :: OS Independent
Requires-Python: >=3.7
Requires-Dist: pyOpenSSL
Requires-Dist: signxml
